nyaacli/__init__.py
nyaacli/cli/__init__.py
nyaacli/colors.py
nyaacli/nyaa_search.py
nyaacli/torrenting.py
nyaacli/utils.py
nyaacli-0.3.2.dist-info/entry_points.txt
nyaacli-0.3.2.dist-info/LICENSE
nyaacli-0.3.2.dist-info/WHEEL
nyaacli-0.3.2.dist-info/METADATA
nyaacli-0.3.2.dist-info/RECORD
