Metadata-Version: 2.1
Name: nyaacli
Version: 0.3.2
Summary: A CLI for downloading Anime from https://nyaa.si
Home-page: https://github.com/johnvictorfs/nyaa-cli
License: MIT
Keywords: CLI,anime
Author: John Victor
Author-email: johnvfs@protonmail.com
Requires-Python: >=3.6.3,<4.0.0
Classifier: Environment :: Console
Classifier: License :: OSI Approved :: MIT License
Classifier: Programming Language :: Python :: 3
Classifier: Programming Language :: Python :: 3.10
Classifier: Programming Language :: Python :: 3.6
Classifier: Programming Language :: Python :: 3.7
Classifier: Programming Language :: Python :: 3.8
Classifier: Programming Language :: Python :: 3.9
Requires-Dist: click (==7.1.2)
Requires-Dist: colorama (==0.4.4)
Requires-Dist: dataclasses (>=0.8,<0.9); python_version >= "3.6" and python_version < "3.7"
Requires-Dist: feedparser (==6.0.2)
Requires-Dist: guessit (==3.2.0)
Requires-Dist: questionary (==1.10.0)
Requires-Dist: rich (>=12.2.0,<12.3.0)
Project-URL: Repository, https://github.com/johnvictorfs/nyaa-cli
